file_parser_lib/__init__.py
file_parser_lib/core.py
file_parser_lib/exceptions.py
file_parser_lib/parser/__init__.py
file_parser_lib/parser/audio.py
file_parser_lib/parser/file.py
file_parser_lib/parser/image.py
file_parser_lib/parser/unified_parser.py
file_parser_lib/utils/paragraph.py
file_parser_lib/utils/validSentence.py
file_parser_lib/utils/classifers/sustainability_hf.py
file_parser_lib/utils/s3/upload.py
file_parser_lib-0.1.0.dist-info/METADATA
file_parser_lib-0.1.0.dist-info/WHEEL
file_parser_lib-0.1.0.dist-info/top_level.txt
file_parser_lib-0.1.0.dist-info/RECORD
