Metadata-Version: 2.2
Name: file_parser_lib
Version: 0.1.0
Summary: A library for parsing various file types including images and audio
Author-email: Vaia <foundersoffice@vaiaclimate.com>
Project-URL: Homepage, https://github.com/founders-vaia/file_parser_lib
Project-URL: Bug Tracker, https://github.com/founders-vaia/file_parser_lib/issues
Classifier: Programming Language :: Python :: 3
Classifier: License :: OSI Approved :: MIT License
Classifier: Operating System :: OS Independent
Requires-Python: >=3.7
Requires-Dist: mimetypes
